tacview_client/__init__.py
tacview_client/__main__.py
tacview_client/cli.py
tacview_client/client.py
tacview_client/config.py
tacview_client/copy_writer.py
tacview_client/cython_funs.c
tacview_client/cython_funs.pyx
tacview_client/db.py
tacview_client/serve_file.py
tacview_client/weapon-db.csv
tacview_client-0.3.5.dist-info/entry_points.txt
tacview_client-0.3.5.dist-info/LICENSE
tacview_client-0.3.5.dist-info/METADATA
tacview_client-0.3.5.dist-info/WHEEL
tacview_client-0.3.5.dist-info/RECORD
